khx_color_lines/__init__.py
khx_color_lines/cli.py
khx_color_lines-0.2.0.dist-info/METADATA
khx_color_lines-0.2.0.dist-info/WHEEL
khx_color_lines-0.2.0.dist-info/entry_points.txt
khx_color_lines-0.2.0.dist-info/licenses/LICENSE
khx_color_lines-0.2.0.dist-info/RECORD
