Metadata-Version: 2.4
Name: khx_color_lines
Version: 0.2.0
Summary: Print five colored lines in the terminal (Windows/macOS/Linux).
Author: Khader Abueltayef
License: MIT
License-File: LICENSE
Keywords: ansi,colors,lines,terminal
Classifier: License :: OSI Approved :: MIT License
Classifier: Operating System :: OS Independent
Classifier: Programming Language :: Python :: 3
Requires-Python: >=3.9
Requires-Dist: colorama>=0.4.6
